annotex/__init__.py
annotex/main.py
annotex/core/__init__.py
annotex/core/annotation_engine.py
annotex/core/dataset_manager.py
annotex/gui/__init__.py
annotex/gui/advanced_gui.py
annotex/gui/python
annotex/utils/__init__.py
annotex/utils/helpers.py
annotex-2.0.9.dist-info/licenses/LICENSE
annotex-2.0.9.dist-info/METADATA
annotex-2.0.9.dist-info/WHEEL
annotex-2.0.9.dist-info/entry_points.txt
annotex-2.0.9.dist-info/top_level.txt
annotex-2.0.9.dist-info/RECORD
