Metadata-Version: 2.4
Name: annotex
Version: 2.0.9
Summary: Annotation Tool for Computer Vision Datasets
Home-page: https://github.com/RandikaKM/annotex
Author: Randika K. Makumbura
Author-email: "Randika K. Makumbura" <randikamk.96@gmail.com>
License: RKM
Project-URL: Homepage, https://github.com/RandikaKM/annotex
Project-URL: Repository, https://github.com/RandikaKM/annotex
Project-URL: Bug Tracker, https://github.com/RandikaKM/annotex/issues
Keywords: annotation,computer-vision,AI,machine-learning,YOLO,dataset
Classifier: Development Status :: 4 - Beta
Classifier: Intended Audience :: Developers
Classifier: Intended Audience :: Science/Research
Classifier: Topic :: Scientific/Engineering :: Artificial Intelligence
Classifier: Programming Language :: Python :: 3
Classifier: Programming Language :: Python :: 3.8
Classifier: Programming Language :: Python :: 3.9
Classifier: Programming Language :: Python :: 3.10
Classifier: Programming Language :: Python :: 3.11
Classifier: Operating System :: OS Independent
Requires-Python: >=3.8
License-File: LICENSE
Requires-Dist: numpy>=1.21.0
Requires-Dist: opencv-python>=4.5.0
Requires-Dist: Pillow>=8.0.0
Requires-Dist: PyYAML>=5.4.0
Requires-Dist: ultralytics>=8.0.0
Provides-Extra: gpu
Requires-Dist: torch>=1.9.0; extra == "gpu"
Requires-Dist: torchvision>=0.10.0; extra == "gpu"
Provides-Extra: dev
Requires-Dist: pytest>=6.0.0; extra == "dev"
Requires-Dist: black>=21.0.0; extra == "dev"
Requires-Dist: flake8>=3.9.0; extra == "dev"
Requires-Dist: mypy>=0.910; extra == "dev"
Requires-Dist: pre-commit>=2.15.0; extra == "dev"
Provides-Extra: docs
Requires-Dist: sphinx>=4.0.0; extra == "docs"
Requires-Dist: sphinx-rtd-theme>=0.5.0; extra == "docs"
Requires-Dist: myst-parser>=0.15.0; extra == "docs"
Dynamic: author
Dynamic: home-page
Dynamic: license-file
Dynamic: requires-python
